tscat_gui/__init__.py
tscat_gui/app.py
tscat_gui/edit.py
tscat_gui/logger.py
tscat_gui/metadata.py
tscat_gui/predicate.py
tscat_gui/state.py
tscat_gui/undo.py
tscat_gui/model_base/__init__.py
tscat_gui/model_base/constants.py
tscat_gui/tscat_driver/__init__.py
tscat_gui/tscat_driver/actions.py
tscat_gui/tscat_driver/catalog_model.py
tscat_gui/tscat_driver/driver.py
tscat_gui/tscat_driver/mime.py
tscat_gui/tscat_driver/model.py
tscat_gui/tscat_driver/nodes.py
tscat_gui/tscat_driver/tscat_root_model.py
tscat_gui/utils/__init__.py
tscat_gui/utils/editable_label.py
tscat_gui/utils/flow_layout.py
tscat_gui/utils/helper.py
tscat_gui/utils/import_export.py
tscat_gui/utils/keyword_list.py
tscat_gui-0.6.0.dist-info/licenses/LICENSE
tscat_gui-0.6.0.dist-info/WHEEL
tscat_gui-0.6.0.dist-info/METADATA
tscat_gui-0.6.0.dist-info/RECORD
