Metadata-Version: 2.4
Name: tscat_gui
Version: 0.6.0
Summary: Time-series catalogue - graphical user interface.
Keywords: satellite,plasma-physics,nasa-data,amda,cdpp,SciQLop
Author-email: Patrick Boettcher <p@yai.se>
Maintainer-email: Patrick Boettcher <p@yai.se>, Alexis Jeandet <alexis.jeandet@member.fsf.org>
Requires-Python: >=3.8
Classifier: Development Status :: 4 - Beta
Classifier: Intended Audience :: Science/Research
Classifier: License :: OSI Approved :: GNU General Public License v3 (GPLv3)
Classifier: Natural Language :: English
Classifier: Programming Language :: Python :: 3
Classifier: Programming Language :: Python :: 3.8
Classifier: Programming Language :: Python :: 3.9
Classifier: Programming Language :: Python :: 3.10
Classifier: Programming Language :: Python :: 3.11
Classifier: Programming Language :: Python :: 3.12
License-File: LICENSE
Requires-Dist: PySide6
Requires-Dist: tscat==0.4.*
Requires-Dist: sphinx ; extra == "doc"
Requires-Dist: sphinx_rtd_theme ; extra == "doc"
Requires-Dist: sphinx-autodoc-typehints ; extra == "doc"
Requires-Dist: flake8 ; extra == "test"
Requires-Dist: appdirs-stubs ; extra == "test"
Requires-Dist: pytest>=4.6.5 ; extra == "test"
Requires-Dist: pytest ; extra == "test"
Requires-Dist: pytest-pep8 ; extra == "test"
Requires-Dist: pytest-cov ; extra == "test"
Requires-Dist: pytest-timeout ; extra == "test"
Requires-Dist: ddt ; extra == "test"
Project-URL: documentation, https://github.com/SciQLop/tscat_gui
Project-URL: homepage, https://github.com/SciQLop/tscat_gui
Project-URL: repository, https://github.com/SciQLop/tscat_gui
Provides-Extra: doc
Provides-Extra: test
